a_pandas_ex_google_book_search_to_df/LICENSE
a_pandas_ex_google_book_search_to_df/README.MD
a_pandas_ex_google_book_search_to_df/__init__.py
a_pandas_ex_google_book_search_to_df/requirements.txt
a_pandas_ex_google_book_search_to_df/thirdparty.json
a_pandas_ex_google_book_search_to_df-0.10.dist-info/LICENSE.rst
a_pandas_ex_google_book_search_to_df-0.10.dist-info/METADATA
a_pandas_ex_google_book_search_to_df-0.10.dist-info/WHEEL
a_pandas_ex_google_book_search_to_df-0.10.dist-info/top_level.txt
a_pandas_ex_google_book_search_to_df-0.10.dist-info/RECORD
